rest_framework_dataclasses/__init__.py
rest_framework_dataclasses/field_utils.py
rest_framework_dataclasses/fields.py
rest_framework_dataclasses/py.typed
rest_framework_dataclasses/serializers.py
rest_framework_dataclasses/types.py
rest_framework_dataclasses/typing_utils.py
djangorestframework_dataclasses_piti-0.10.dist-info/LICENSE
djangorestframework_dataclasses_piti-0.10.dist-info/METADATA
djangorestframework_dataclasses_piti-0.10.dist-info/WHEEL
djangorestframework_dataclasses_piti-0.10.dist-info/top_level.txt
djangorestframework_dataclasses_piti-0.10.dist-info/RECORD
