Metadata-Version: 2.1
Name: djangorestframework-dataclasses-piti
Version: 0.10
Summary: A dataclasses serializer for Django REST Framework(Temporary before PR is merged)
Home-page: https://github.com/piti118/djangorestframework-dataclasses
Author: Piti Ongmongkolkul (Original Author Oxan van Leeuwen)
Author-email: piti118@gmail.com
License: BSD
Platform: UNKNOWN
Classifier: Development Status :: 4 - Beta
Classifier: Environment :: Web Environment
Classifier: Framework :: Django
Classifier: Framework :: Django :: 2.0
Classifier: Framework :: Django :: 2.1
Classifier: Framework :: Django :: 2.2
Classifier: Framework :: Django :: 3.0
Classifier: Framework :: Django :: 3.1
Classifier: Framework :: Django :: 3.2
Classifier: Intended Audience :: Developers
Classifier: License :: OSI Approved :: BSD License
Classifier: Operating System :: OS Independent
Classifier: Programming Language :: Python
Classifier: Programming Language :: Python :: 3.7
Classifier: Programming Language :: Python :: 3.8
Classifier: Programming Language :: Python :: 3.9
Classifier: Programming Language :: Python :: 3.10
Classifier: Topic :: Internet :: WWW/HTTP
Classifier: Topic :: Software Development :: Libraries :: Application Frameworks
Classifier: Topic :: Software Development :: Libraries :: Python Modules
Classifier: Typing :: Typed
Requires-Python: >=3.7
License-File: LICENSE
Requires-Dist: django (>=2.0)
Requires-Dist: djangorestframework (>=3.9)
Requires-Dist: typing-extensions (>=3.7.4) ; python_version < "3.8"
